calculate_my_score/__init__.py
calculate_my_score/main.py
calculate_my_score-0.1.2.dist-info/entry_points.txt
calculate_my_score-0.1.2.dist-info/LICENSE
calculate_my_score-0.1.2.dist-info/WHEEL
calculate_my_score-0.1.2.dist-info/METADATA
calculate_my_score-0.1.2.dist-info/RECORD
