Metadata-Version: 2.1
Name: calculate-my-score
Version: 0.1.2
Summary: Calculate your score by one simple command!
Home-page: https://github.com/jochman/calculate-my-score
License: MIT
Author: Bar Hochman
Requires-Python: >=3.8,<4.0
Classifier: License :: OSI Approved :: MIT License
Classifier: Programming Language :: Python :: 3
Classifier: Programming Language :: Python :: 3.10
Classifier: Programming Language :: Python :: 3.8
Classifier: Programming Language :: Python :: 3.9
Requires-Dist: pytest (>=7.1.2,<8.0.0)
Requires-Dist: rich (>=12.5.1,<13.0.0)
Requires-Dist: typer (>=0.6.1,<0.7.0)
Project-URL: Repository, https://github.com/jochman/calculate-my-score
